aionationstates/__init__.py
aionationstates/happenings.py
aionationstates/nation_.py
aionationstates/ns_to_human.py
aionationstates/ratelimit.py
aionationstates/region_.py
aionationstates/session.py
aionationstates/shared.py
aionationstates/utils.py
aionationstates/wa_.py
aionationstates/world_.py
aionationstates-0.4.9.dist-info/LICENSE
aionationstates-0.4.9.dist-info/METADATA
aionationstates-0.4.9.dist-info/WHEEL
aionationstates-0.4.9.dist-info/top_level.txt
aionationstates-0.4.9.dist-info/RECORD
