Metadata-Version: 2.1
Name: aionationstates
Version: 0.4.9
Summary: An asyncio wrapper for the NationStates API
Home-page: https://github.com/micha030201/aionationstates
Author: Михаил Лебедев
Author-email: micha030201@gmail.com
License: GPLv3
Keywords: API nationstates
Platform: UNKNOWN
Classifier: Development Status :: 3 - Alpha
Classifier: Intended Audience :: Developers
Classifier: Topic :: Internet
Classifier: Topic :: Games/Entertainment :: Simulation
Classifier: License :: OSI Approved :: GNU General Public License v3 (GPLv3)
Classifier: Programming Language :: Python :: 3.6
License-File: LICENSE
Requires-Dist: aiohttp
